{
  "project_info": {
    "project_number": "852393992397",
    "project_id": "ecosight-704c9",
    "storage_bucket": "ecosight-704c9.firebasestorage.app"
  },
  "client": [
    {
      "client_info": {
        "mobilesdk_app_id": "1:852393992397:android:f25bd3e9003d11cc848984",
        "android_client_info": {
          "package_name": "com.example.ecosight_app"
        }
      },
      "oauth_client": [],
      "api_key": [
        {
          "current_key": "AIzaSyAKIGFkVTAwefz_oQBJuIi3bN9lHnnJxPw"
        }
      ],
      "services": {
        "appinvite_service": {
          "other_platform_oauth_client": []
        }
      }
    }
  ],
  "configuration_version": "1"
}